backupchan/__init__.py
backupchan/api.py
backupchan/connection.py
backupchan/models.py
backupchan_client_lib-1.4.1.dist-info/licenses/LICENSE
backupchan_client_lib-1.4.1.dist-info/METADATA
backupchan_client_lib-1.4.1.dist-info/WHEEL
backupchan_client_lib-1.4.1.dist-info/top_level.txt
backupchan_client_lib-1.4.1.dist-info/RECORD
