Metadata-Version: 2.4
Name: backupchan-client-lib
Version: 1.4.1
Summary: Library for interfacing with Backup-chan.
Author-email: Moltony <koronavirusnyj@gmail.com>
License: BSD-3-Clause
Project-URL: Homepage, https://github.com/Backupchan/client-lib
Project-URL: Repository, https://github.com/Backupchan/client-lib.git
Project-URL: Issues, https://github.com/Backupchan/client-lib/issues
Project-URL: Changelog, https://github.com/Backupchan/client-lib/blob/main/CHANGELOG.md
Classifier: Development Status :: 5 - Production/Stable
Classifier: License :: OSI Approved :: BSD License
Classifier: Natural Language :: English
Classifier: Operating System :: OS Independent
Classifier: Programming Language :: Python :: 3 :: Only
Classifier: Topic :: System :: Archiving :: Backup
Classifier: Topic :: Software Development :: Libraries
Classifier: Typing :: Typed
License-File: LICENSE
Requires-Dist: requests
Provides-Extra: dev
Requires-Dist: pytest; extra == "dev"
Requires-Dist: requests-mock; extra == "dev"
Dynamic: license-file
